 <?xml version="1.0" encoding="UTF-8" standalone="yes"?>

======================================================================

<!--
 TABOO
-->
<!--

	ETIQUETAS:
	
	- 1SerieTitle:"TABOO", SerieTemp:"TEMPORADA 1", SerieID:"SERIETEMP1", SerieIDT:"TORRENTTEMP1", SerieThumbail:"https://image.tmdb.org/t/p/w600_and_h900_bestv2/om1wVOuEtwH3krHutIWO9sJzkS5.jpg",

	
-->
======================================================================
			"Tag= TORRENTTEMP1, "
			<item>
			<title>1x01 - Capitulo 1</title>
			<torrent>magnet:?xt=urn:btih:4a76e35196d96f66c516920b8752e4b8710ff47f</torrent>
			</item>
======================================================================
			"Tag= TORRENTTEMP1, "
			<item>
			<title>1x02 - Capitulo 2</title>
			<torrent>magnet:?xt=urn:btih:827e314bcadfdb01a514ccfca76113d076fab3b2</torrent>
			</item>
======================================================================
			"Tag= TORRENTTEMP1, "
			<item>
			<title>1x03 - Capitulo 3</title>
			<torrent>magnet:?xt=urn:btih:7ff3e69d81502c470b37b501f5affb408fd62487</torrent>
			</item>
======================================================================
			"Tag= TORRENTTEMP1, "
			<item>
			<title>1x04 - Capitulo 4</title>
			<torrent>magnet:?xt=urn:btih:fb3d9bb7227d5c1e12f96db689cc0b9636b00efd</torrent>
			</item>
======================================================================
			"Tag= TORRENTTEMP1, "
			<item>
			<title>1x05 - Capitulo 5</title>
			<torrent>magnet:?xt=urn:btih:19185aad199e1f587bc1a59ccab0a8dc3b0113d6</torrent>
			</item>
======================================================================
			"Tag= TORRENTTEMP1, "
			<item>
			<title>1x06 - Capitulo 6</title>
			<torrent>magnet:?xt=urn:btih:1e010c31c70f5f7a7692863bbdccafc0b0b88892</torrent>
			</item>
======================================================================
			"Tag= TORRENTTEMP1, "
			<item>
			<title>1x07 - Capitulo 7</title>
			<torrent>magnet:?xt=urn:btih:f4bb53f7fb5c5555ec4f0510c1c4b423c416fc17</torrent>
			</item>
======================================================================
			"Tag= TORRENTTEMP1, "
			<item>
			<title>1x08 - Capitulo 8</title>
			<torrent>magnet:?xt=urn:btih:417a9cbb75617bbab4b8a5d9abdd185ada4d4897</torrent>
			</item>
======================================================================
======================================================================
======================================================================
======================================================================