 <?xml version="1.0" encoding="UTF-8" standalone="yes"?>

======================================================================

<!--
 DEALER (CAID)
-->
<!--

	ETIQUETAS:
	
	- 1SerieTitle:"DEALER (CAID)", SerieTemp:"MINI SERIE", SerieID:"SERIETEMP1", SerieIDT:"TORRENTTEMP1", SerieThumbail:"https://www.themoviedb.org/t/p/original/ajiMiKtAsWeccVCEvOSt7efY78g.jpg",

	
-->
======================================================================
			"Tag= TORRENTTEMP1, "
			<item>
			<title> - [COLOR yellow]CALIDAD 720</title><titleGdrive></titleGdrive>      
			<torrent></torrent>
			</item>
======================================================================
			"Tag= TORRENTTEMP1, "
			<item>
			<title> - Capitulos 1 a 10</title><titleGdrive></titleGdrive>      
			<torrent>magnet:?xt=urn:btih:5421B1B172D109189276BF54C74903EB9C693160</torrent>
			</item>
======================================================================
======================================================================
			"Tag= TORRENTTEMP1, "
			<item>
			<title> - </title><titleGdrive></titleGdrive>      
			<torrent></torrent>
			</item>
======================================================================
			"Tag= TORRENTTEMP1, "
			<item>
			<title> - [COLOR yellow]CALIDAD HDTV</title><titleGdrive></titleGdrive>      
			<torrent></torrent>
			</item>
======================================================================
			"Tag= TORRENTTEMP1, "
			<item>
			<title> - Capitulos 1 a 10</title><titleGdrive></titleGdrive>      
			<torrent>magnet:?xt=urn:btih:1D9300EA74E13D7C1708D55BCBDF7908C49EDDE5</torrent>
			</item>
======================================================================
======================================================================
======================================================================
			"Tag= SERIETEMP1, ORRENTTEMP1, "
			<item>
			<title>1x01 - Spielberg</title><titleGdrive></titleGdrive>      
			<link>https://femax20.com/v/4ym0-bz7ldnxkjp</link>  
			<link2>https://femax20.com/v/xy4lzc5k88gkw1-</link2>  
			<link3>https://vidia.tv/NO_LINK</link3>  
			<link4>https://vidia.tv/NO_LINK</link4>  
			<link5>https://vidia.tv/NO_LINK</link5>
			<GDRIVE>https://drive.google.com/file/d/1Zwtu4epF3ewdC4lGRaAfiXcdGvdhDSWQ/view?usp=sharing</GDRIVE>
			<torrent></torrent>
			</item>
======================================================================
			"Tag= SERIETEMP1, ORRENTTEMP1, "
			<item>
			<title>1x02 - Raya a raya</title><titleGdrive></titleGdrive>      
			<link>https://femax20.com/v/dnm0lhxdnk7-5jj</link>  
			<link2>https://femax20.com/v/53dr2udejj3mq14</link2>  
			<link3>https://vidia.tv/NO_LINK</link3>  
			<link4>https://vidia.tv/NO_LINK</link4>  
			<link5>https://vidia.tv/NO_LINK</link5>
			<GDRIVE>https://drive.google.com/file/d/11s9kNtZgWX4NABEr0aeylFfSur357VJu/view?usp=sharing</GDRIVE>
			<torrent></torrent>
			</item>
======================================================================
			"Tag= SERIETEMP1, ORRENTTEMP1, "
			<item>
			<title>1x03 - Drogata</title><titleGdrive></titleGdrive>      
			<link>https://femax20.com/v/2lk7-b2jk63m7el</link>  
			<link2>https://femax20.com/v/e82ryf-xnnjjgnk</link2>  
			<link3>https://vidia.tv/NO_LINK</link3>  
			<link4>https://vidia.tv/NO_LINK</link4>  
			<link5>https://vidia.tv/NO_LINK</link5>
			<GDRIVE>https://drive.google.com/file/d/1e5P9mP3JHERk5nzoRMwM7Dex0spQkubn/view?usp=sharing</GDRIVE>
			<torrent></torrent>
			</item>
======================================================================
			"Tag= SERIETEMP1, ORRENTTEMP1, "
			<item>
			<title>1x04 - ¡La pasma!</title><titleGdrive></titleGdrive>      
			<link>https://femax20.com/v/8ne4-h8761ydmqr</link>  
			<link2>https://femax20.com/v/1w32kujk22lgxzl</link2>  
			<link3>https://vidia.tv/NO_LINK</link3>  
			<link4>https://vidia.tv/NO_LINK</link4>  
			<link5>https://vidia.tv/NO_LINK</link5>
			<GDRIVE>https://drive.google.com/file/d/1a-WbwNEG6eChYZZh2A23_l7yCQYxhUDb/view?usp=sharing</GDRIVE>
			<torrent></torrent>
			</item>
======================================================================
			"Tag= SERIETEMP1, ORRENTTEMP1, "
			<item>
			<title>1x05 - Mercancía</title><titleGdrive></titleGdrive> 
			<link>https://femax20.com/v/jd854sd51z28zwm</link>  
			<link2>https://femax20.com/v/3w6dyum3xxn28l-</link2>  
			<link3>https://vidia.tv/NO_LINK</link3>  
			<link4>https://vidia.tv/NO_LINK</link4>  
			<link5>https://vidia.tv/NO_LINK</link5>
			<GDRIVE>https://drive.google.com/file/d/1K_c1DPmBK_1EuyPCaZB-Yicg65A46C6H/view?usp=sharing</GDRIVE>
			<torrent></torrent>
			</item>
======================================================================
			"Tag= SERIETEMP1, ORRENTTEMP1, "
			<item>
			<title>1x06 - Estilo libre</title><titleGdrive></titleGdrive>      
			<link>https://femax20.com/v/0qp4-blnw2n600r</link>  
			<link2>https://femax20.com/v/k7y5mu35gg7z515</link2>  
			<link3>https://vidia.tv/NO_LINK</link3>  
			<link4>https://vidia.tv/NO_LINK</link4>  
			<link5>https://vidia.tv/NO_LINK</link5>
			<GDRIVE>https://drive.google.com/file/d/1LYkvfZMIV0Stpbc0k0yM5bdH93o-iLLm/view?usp=sharing</GDRIVE>
			<torrent></torrent>
			</item>
======================================================================
			"Tag= SERIETEMP1, ORRENTTEMP1, "
			<item>
			<title>1x07 - Unos petas</title><titleGdrive></titleGdrive>      
			<link>https://femax20.com/v/3ezd-im8478kxjx</link>  
			<link2>https://femax20.com/v/1w32kujk22l3jx8</link2>  
			<link3>https://vidia.tv/NO_LINK</link3>  
			<link4>https://vidia.tv/NO_LINK</link4>  
			<link5>https://vidia.tv/NO_LINK</link5>
			<GDRIVE>https://drive.google.com/file/d/15rKsAPwZ3h9WkFs52n8zHgUK6lEOmA8y/view?usp=sharing</GDRIVE>
			<torrent></torrent>
			</item>
======================================================================
			"Tag= SERIETEMP1, ORRENTTEMP1, "
			<item>
			<title>1x08 - Lengua suelta</title><titleGdrive></titleGdrive>      
			<link>https://femax20.com/v/lr-57cnpy6p1m28</link>  
			<link2>https://femax20.com/v/-wzmxupy11ny41n</link2>  
			<link3>https://vidia.tv/NO_LINK</link3>  
			<link4>https://vidia.tv/NO_LINK</link4>  
			<link5>https://vidia.tv/NO_LINK</link5>
			<GDRIVE>https://drive.google.com/file/d/1yhfpV0m4Jn6zT4Mufndy5uFc01N1JouD/view?usp=sharing</GDRIVE>
			<torrent></torrent>
			</item>
======================================================================
			"Tag= SERIETEMP1, ORRENTTEMP1, "
			<item>
			<title>1x09 - Matones</title><titleGdrive></titleGdrive>      
			<link>https://femax20.com/v/zn8lxhjkn4key-1</link>  
			<link2>https://femax20.com/v/rzywphe8gg5-w44</link2>  
			<link3>https://vidia.tv/NO_LINK</link3>  
			<link4>https://vidia.tv/NO_LINK</link4>  
			<link5>https://vidia.tv/NO_LINK</link5>
			<GDRIVE>https://drive.google.com/file/d/1dDAAf9CVHKfanmd1jSN8DEYwbX2ndrqo/view?usp=sharing</GDRIVE>
			<torrent></torrent>
			</item>
======================================================================
			"Tag= SERIETEMP1, ORRENTTEMP1, "
			<item>
			<title>1x10 - El líder</title><titleGdrive></titleGdrive>      
			<link>https://femax20.com/v/5xqr-bdxg0xq080</link>  
			<link2>https://femax20.com/v/k7y5mu35gg7x33r</link2>  
			<link3>https://vidia.tv/NO_LINK</link3>  
			<link4>https://vidia.tv/NO_LINK</link4>  
			<link5>https://vidia.tv/NO_LINK</link5>
			<GDRIVE>https://drive.google.com/file/d/1wckzUEE6ppN6DsZfUdim86QW142wzJQ3/view?usp=sharing</GDRIVE>
			<torrent></torrent>
			</item>
======================================================================
======================================================================
======================================================================
======================================================================
======================================================================