 <?xml version="1.0" encoding="UTF-8" standalone="yes"?>

======================================================================

<!--
 EL BOSQUE INFINITO
-->
<!--

	ETIQUETAS:
	
	- 1SerieTitle:"EL BOSQUE INFINITO", SerieTemp:"MINI SERIE", SerieID:"SERIETEMP1", SerieIDT:"TORRENTTEMP1", SerieThumbail:"https://www.themoviedb.org/t/p/original/wzi7TMZyh6PyTeJweFbbSV4kadT.jpg",

	
-->
======================================================================
			"Tag= TORRENTTEMP1, "
			<item>
			<title>1x01 - Nueva Francia</title>   
			<torrent>https://raw.githubusercontent.com/staffcf/canto/main/MUSICA/Torrents/Series/El.bosque.infinito/1x01.-El.bosque.infinito.-.1080.-.CristalAzul.mkv.torrent</torrent>
			</item>
======================================================================
			"Tag= TORRENTTEMP1, "
			<item>
			<title>1x02 - El Rey Tortuga</title>  
			<torrent>https://raw.githubusercontent.com/staffcf/canto/main/MUSICA/Torrents/Series/El.bosque.infinito/1x02.-El.bosque.infinito.-.1080.-.CristalAzul.mkv.torrent</torrent>
			</item>
======================================================================
			"Tag= TORRENTTEMP1, "
			<item>
			<title>1x03 - La ciruela azucarada</title> 
			<torrent>https://raw.githubusercontent.com/staffcf/canto/main/MUSICA/Torrents/Series/El.bosque.infinito/1x03.-El.bosque.infinito.-.1080.-.CristalAzul.mkv.torrent</torrent>
			</item>
======================================================================
			"Tag= TORRENTTEMP1, "
			<item>
			<title>1x04 - La ley de dos</title>   
			<torrent>https://raw.githubusercontent.com/staffcf/canto/main/MUSICA/Torrents/Series/El.bosque.infinito/1x04.-El.bosque.infinito.-.1080.-.CristalAzul.mkv.torrent</torrent>
			</item>
======================================================================
			"Tag= TORRENTTEMP1, "
			<item>
			<title>1x05 - Suero de la leche</title> 
			<torrent>https://raw.githubusercontent.com/staffcf/canto/main/MUSICA/Torrents/Series/El.bosque.infinito/1x05.-El.bosque.infinito.-.1080.-.CristalAzul.mkv.torrent</torrent>
			</item>
======================================================================
			"Tag= TORRENTTEMP1, "
			<item>
			<title>1x06 - El bamboleo</title>  
			<torrent>https://raw.githubusercontent.com/staffcf/canto/main/MUSICA/Torrents/Series/El.bosque.infinito/1x06.-El.bosque.infinito.-.1080.-.CristalAzul.mkv.torrent</torrent>
			</item>
======================================================================
			"Tag= TORRENTTEMP1, "
			<item>
			<title>1x07 - Abejas en una botella</title> 
			<torrent>https://raw.githubusercontent.com/staffcf/canto/main/MUSICA/Torrents/Series/El.bosque.infinito/1x07.-El.bosque.infinito.-.1080.-.CristalAzul.mkv.torrent</torrent>
			</item>
======================================================================
			"Tag= TORRENTTEMP1, "
			<item>
			<title>1x08 - El sol negro</title>   
			<torrent>https://raw.githubusercontent.com/staffcf/canto/main/MUSICA/Torrents/Series/El.bosque.infinito/1x08.-El.bosque.infinito.-.1080.-.CristalAzul.mkv.torrent</torrent>
			</item>
======================================================================
======================================================================
======================================================================
======================================================================
======================================================================