 <?xml version="1.0" encoding="UTF-8" standalone="yes"?>

======================================================================

<!--
 EL LIBRO DE BOBA FETT
-->
<!--

	ETIQUETAS:
	
	- 1SerieTitle:"EL LIBRO DE BOBA FETT", SerieTemp:"TEMPORADA 1", SerieID:"SERIETEMP1", SerieIDT:"TORRENTTEMP1", SerieThumbail:"https://www.themoviedb.org/t/p/original/7V6kUmFifqlUERsKFBqrZx9Pxxg.jpg",
	
-->
======================================================================
			"Tag= TORRENTTEMP1, "
			<item>
			<title> - [COLOR yellow]CALIDAD 1080</title>
			<torrent></torrent>
			</item>
======================================================================
			"Tag= TORRENTTEMP1, "
			<item>
			<title>1x01 - Forastero en tierra extraña</title>
			<torrent>https://raw.githubusercontent.com/staffcf/canto/main/MUSICA/Torrents/Series/El.libro.de.Boba.Fett/1x01.-E.L.D.B.F.-.1080.-.CristalAzul.mkv.torrent</torrent>	magnet:?xt=urn:btih:0E2DF42F00A0484AC5D8A7A07CEF4EA884BBB508&dn=HD1080
			</item>
======================================================================
			"Tag= TORRENTTEMP1, "
			<item>
			<title>1x02 - Las tribus de Tatooine</title>
			<torrent>https://raw.githubusercontent.com/staffcf/canto/main/MUSICA/Torrents/Series/El.libro.de.Boba.Fett/1x02.-E.L.D.B.F.-.1080.-.CristalAzul.mkv.torrent</torrent>
			</item>
======================================================================
			"Tag= TORRENTTEMP1, "
			<item>
			<title>1x03 - Las calles de Mos Espa</title>
			<torrent>https://raw.githubusercontent.com/staffcf/canto/main/MUSICA/Torrents/Series/El.libro.de.Boba.Fett/1x03.-E.L.D.B.F.-.1080.-.CristalAzul.mkv.torrent</torrent>
			</item>
======================================================================
			"Tag= TORRENTTEMP1, "
			<item>
			<title>1x04 - Capitulo 4 [COLOR orangered](PROXIMAMENTE)</title>
			<torrent></torrent>
			</item>
======================================================================
			"Tag= TORRENTTEMP1, "
			<item>
			<title>1x05 - Capitulo 5 [COLOR orangered](PROXIMAMENTE)</title>
			<torrent></torrent>
			</item>
======================================================================
			"Tag= TORRENTTEMP1, "
			<item>
			<title>1x06 - Capitulo 6 [COLOR orangered](PROXIMAMENTE)</title>
			<torrent></torrent>
			</item>
======================================================================
			"Tag= TORRENTTEMP1, "
			<item>
			<title>1x07 - Capitulo 7 [COLOR orangered](PROXIMAMENTE)</title>
			<torrent></torrent>
			</item>
======================================================================
======================================================================
======================================================================
======================================================================
======================================================================
======================================================================
			"Tag= TORRENTTEMP1, "
			<item>
			<title> - </title>
			<torrent></torrent>
			</item>
======================================================================
			"Tag= TORRENTTEMP1, "
			<item>
			<title> - [COLOR yellow]CALIDAD 720</title>
			<torrent></torrent>
			</item>
======================================================================
			"Tag= TORRENTTEMP1, "
			<item>
			<title>1x01 - Forastero en tierra extraña</title>
			<torrent>magnet:?xt=urn:btih:B0A7E1BDFE76D2CAF7679F96D9CE6E7A5E976076&dn=HD720</torrent>
			</item>
======================================================================
			"Tag= TORRENTTEMP1, "
			<item>
			<title>1x02 - Las tribus de Tatooine</title>
			<torrent>magnet:?xt=urn:btih:F232FD7443D299977ADE36FEE996827F99A488BE&dn=HD720</torrent>
			</item>
======================================================================
			"Tag= TORRENTTEMP1, "
			<item>
			<title>1x03 - Las calles de Mos Espa</title>
			<torrent>magnet:?xt=urn:btih:3F182F85DE449339CA9BE9E410CE586179863B95&dn=HD720</torrent>
			</item>
======================================================================
			"Tag= TORRENTTEMP1, "
			<item>
			<title>1x04 - Capitulo 4 [COLOR orangered](PROXIMAMENTE)</title>
			<torrent></torrent>
			</item>
======================================================================
			"Tag= TORRENTTEMP1, "
			<item>
			<title>1x05 - Capitulo 5 [COLOR orangered](PROXIMAMENTE)</title>
			<torrent></torrent>
			</item>
======================================================================
			"Tag= TORRENTTEMP1, "
			<item>
			<title>1x06 - Capitulo 6 [COLOR orangered](PROXIMAMENTE)</title>
			<torrent></torrent>
			</item>
======================================================================
			"Tag= TORRENTTEMP1, "
			<item>
			<title>1x07 - Capitulo 7 [COLOR orangered](PROXIMAMENTE)</title>
			<torrent></torrent>
			</item>
======================================================================
======================================================================
======================================================================
======================================================================
			"Tag= TORRENTTEMP1, "
			<item>
			<title> - </title>
			<torrent></torrent>
			</item>
======================================================================
			"Tag= TORRENTTEMP1, "
			<item>
			<title> - [COLOR yellow]CALIDAD HDTV</title>
			<torrent></torrent>
			</item>
======================================================================
			"Tag= TORRENTTEMP1, "
			<item>
			<title>1x01 - Forastero en tierra extraña</title>
			<torrent>magnet:?xt=urn:btih:5C037D576DBBF3200B77E571A8E42BB4BD5FBAE1&dn=HDTV</torrent>
			</item>
======================================================================
			"Tag= TORRENTTEMP1, "
			<item>
			<title>1x02 - Las tribus de Tatooine</title>
			<torrent>magnet:?xt=urn:btih:E8D4CF10089DAB73F5EF27E61E72D5D0103071DE&dn=HDTV</torrent>
			</item>
======================================================================
			"Tag= TORRENTTEMP1, "
			<item>
			<title>1x03 - Las calles de Mos Espa</title>
			<torrent>magnet:?xt=urn:btih:C2801BAE1C09C93A3F1EE8916C795F4BAB9C89D3&dn=HDTV</torrent>
			</item>
======================================================================
			"Tag= TORRENTTEMP1, "
			<item>
			<title>1x04 - Capitulo 4 [COLOR orangered](PROXIMAMENTE)</title>
			<torrent></torrent>
			</item>
======================================================================
			"Tag= TORRENTTEMP1, "
			<item>
			<title>1x05 - Capitulo 5 [COLOR orangered](PROXIMAMENTE)</title>
			<torrent></torrent>
			</item>
======================================================================
			"Tag= TORRENTTEMP1, "
			<item>
			<title>1x06 - Capitulo 6 [COLOR orangered](PROXIMAMENTE)</title>
			<torrent></torrent>
			</item>
======================================================================
			"Tag= TORRENTTEMP1, "
			<item>
			<title>1x07 - Capitulo 7 [COLOR orangered](PROXIMAMENTE)</title>
			<torrent></torrent>
			</item>
======================================================================
======================================================================
======================================================================
======================================================================
======================================================================