 <?xml version="1.0" encoding="UTF-8" standalone="yes"?>

======================================================================

<!--
 ELFOS
-->
<!--

	ETIQUETAS:
	
	- 1SerieTitle:"ELFOS", SerieTemp:"TEMPORADA 1", SerieID:"SERIETEMP1", SerieIDT:"TORRENTTEMP1", SerieThumbail:"https://www.themoviedb.org/t/p/original/ydAoSBtvi41yMmqkOL7Y43DcbCX.jpg",
	
-->
======================================================================
			"Tag= TORRENTTEMP1, "
			<item>
			<title> - [COLOR yellow]CALIDAD 1080</title>
			<torrent></torrent>
			</item>
======================================================================
			"Tag= TORRENTTEMP1, "
			<item>
			<title>1x0. - Capitulos 1 y 2</title>
			<torrent>magnet:?xt=urn:btih:490F5F407FFE404A31403C27AF253B40F1228187&dn=HD1080</torrent>
			</item>
======================================================================
			"Tag= TORRENTTEMP1, "
			<item>
			<title>1x0. - Capitulos 3 y 4</title>
			<torrent>magnet:?xt=urn:btih:640107E2B9638325F62D95B4505013A7BBE4BE41&dn=HD1080</torrent>
			</item>
======================================================================
			"Tag= TORRENTTEMP1, "
			<item>
			<title>1x0. - Capitulos 5 y 6</title>
			<torrent>magnet:?xt=urn:btih:B45649366E4C206FC2FE07ED75C674DEC2EEDCC4&dn=HD1080</torrent>
			</item>
======================================================================
======================================================================
======================================================================
			"Tag= TORRENTTEMP1, "
			<item>
			<title> - </title>
			<torrent></torrent>
			</item>
======================================================================
			"Tag= TORRENTTEMP1, "
			<item>
			<title> - [COLOR yellow]CALIDAD HDTV</title>
			<torrent></torrent>
			</item>
======================================================================
			"Tag= TORRENTTEMP1, "
			<item>
			<title>1x0. - Capitulos 1 y 2</title>
			<torrent>magnet:?xt=urn:btih:FE51F8DB2DB2C1FCD1D3C7EED5315329CB26F96C&dn=HDTV</torrent>
			</item>
======================================================================
			"Tag= TORRENTTEMP1, "
			<item>
			<title>1x0. - Capitulos 3 y 4</title>
			<torrent>magnet:?xt=urn:btih:792B569C8B0A0B14BB784F2DDFEF5F69F7FF6938&dn=HDTV</torrent>
			</item>
======================================================================
			"Tag= TORRENTTEMP1, "
			<item>
			<title>1x0. - Capitulos 5 y 6</title>
			<torrent>magnet:?xt=urn:btih:23BBB366C34A992A87EE6A163BDFD8D0A6B9663A&dn=HDTV</torrent>
			</item>
======================================================================
======================================================================
======================================================================