 <?xml version="1.0" encoding="UTF-8" standalone="yes"?>

======================================================================

<!--
 KLANGOR
-->
<!--

	ETIQUETAS:
	
	- 1SerieTitle:"KLANGOR", SerieTemp:"TEMPORADA 1", SerieID:"SERIETEMP1", SerieIDT:"TORRENTTEMP1", SerieThumbail:"https://www.themoviedb.org/t/p/original/nYmQNE6uqmPXUQAQE2wHct38MXG.jpg",
	
-->
======================================================================
			"Tag= TORRENTTEMP1, "
			<item>
			<title> - [COLOR yellow]CALIDAD 720</title>
			<torrent></torrent>
			</item>
======================================================================
			"Tag= TORRENTTEMP1, "
			<item>
			<title>1x0. - Capitulo 1</title>
			<torrent>magnet:?xt=urn:btih:F3DFFB3E51CE3D737941A0475CFAB9477F6FB979&dn=HD720</torrent>
			</item>
======================================================================
			"Tag= TORRENTTEMP1, "
			<item>
			<title>1x0. - Capitulos 2 a 5</title>
			<torrent>magnet:?xt=urn:btih:10290B110FF197A5FA7BDE457DAB3BD6DC791084&dn=HD720</torrent>
			</item>
======================================================================
			"Tag= TORRENTTEMP1, "
			<item>
			<title>1x0. - Capitulos 6 a 8</title>
			<torrent>magnet:?xt=urn:btih:270A28D7857CEB0C3D5103E6351681F481E7A752&dn=HD720</torrent>
			</item>
======================================================================
======================================================================
			"Tag= TORRENTTEMP1, "
			<item>
			<title> - </title>
			<torrent></torrent>
			</item>
======================================================================
			"Tag= TORRENTTEMP1, "
			<item>
			<title> - [COLOR yellow]CALIDAD HDTV</title>
			<torrent></torrent>
			</item>
======================================================================
			"Tag= TORRENTTEMP1, "
			<item>
			<title>1x0. - Capitulo 1</title>
			<torrent>magnet:?xt=urn:btih:5F2CC22649D9B743F9336B01DCCC6D7DD2A650DF&dn=HDTV</torrent>
			</item>
======================================================================
			"Tag= TORRENTTEMP1, "
			<item>
			<title>1x0. - Capitulos 2 a 5</title>
			<torrent>magnet:?xt=urn:btih:1925D0155C4E04286788580C94D258E5058D6CAC&dn=HDTV</torrent>
			</item>
======================================================================
			"Tag= TORRENTTEMP1, "
			<item>
			<title>1x0. - Capitulos 6 a 8</title>
			<torrent>magnet:?xt=urn:btih:8F6A3E158A214B30DA63B493856CC5F185EEFDC0&dn=HDTV</torrent>
			</item>
======================================================================
======================================================================
======================================================================