 <?xml version="1.0" encoding="UTF-8" standalone="yes"?>

======================================================================

<!--
 SOCIOS Y SABUESOS
-->
<!--

	ETIQUETAS:
	
	- 1SerieTitle:"SOCIOS Y SABUESOS", SerieTemp:"TEMPORADA 1", SerieID:"SERIETEMP1", SerieIDT:"TORRENTTEMP1", SerieThumbail:"https://www.themoviedb.org/t/p/original/p1hR8mkaK9grxJ5yzIDrBilctaS.jpg",
-->
======================================================================
======================================================================
			"Tag= TORRENTTEMP1, "
			<item>
			<title>1x01 - Siempre y un perro</title>
			<torrent>magnet:?xt=urn:btih:600ADF383DC1FD5028AA8C1E12E6BE836964DBD9&dn=HDTV</torrent>
			</item>
======================================================================
			"Tag= TORRENTTEMP1, "
			<item>
			<title>1x02 - Un buen día para un perro duro</title>
			<torrent>magnet:?xt=urn:btih:6572E83B2205890EC4138B0A67953C9BC18A182A&dn=HD720</torrent>
			</item>
======================================================================
			"Tag= TORRENTTEMP1, "
			<item>
			<title>1x03 - Los diamantes son "prra" siempre</title>
			<torrent>magnet:?xt=urn:btih:B03C05AB50BE34DF631FA6A8FF19928EBE1292D7&dn=HD720</torrent>
			</item>
======================================================================
			"Tag= TORRENTTEMP1, "
			<item>
			<title>1x04 - En la línea de fuego canina</title>
			<torrent>magnet:?xt=urn:btih:231ED958D770BDF121F8FBFD067D12567EB98C12&dn=HD720</torrent>
			</item>
======================================================================
			"Tag= TORRENTTEMP1, "
			<item>
			<title>1x05 - La apestosa ruta de El Dorado</title>
			<torrent>magnet:?xt=urn:btih:8664BC43095908DAD793E681839281C009C9C86A&dn=HDTV</torrent>
			</item>
======================================================================
			"Tag= TORRENTTEMP1, "
			<item>
			<title>1x06 - El fugitivo peludo</title>
			<torrent>magnet:?xt=urn:btih:A02F84E734F128C4ED5C661CA8A32CEBD3E0C0B2&dn=HD720</torrent>
			</item>
======================================================================
			"Tag=  TORRENTTEMP1, "
			<item>
			<title>1x07 - Para servir y aullar</title>
			<torrent>magnet:?xt=urn:btih:C02E09F18306FB292156E442DAE3BEF430F8D8E8&dn=HD720</torrent>
			</item>
======================================================================
			"Tag=  TORRENTTEMP1, "
			<item>
			<title>1x08 - ¡Guau, qué arte!</title>
			<torrent>magnet:?xt=urn:btih:81AE1DE6B64A9EB1DF1174DD199ABB61C4027856&dn=HDTV.propper</torrent>	magnet:?xt=urn:btih:E9C9A058AFF4403A607B57D1DB61A2E4DF884BF1&dn=HDTV
			</item>
======================================================================
			"Tag=  TORRENTTEMP1, "
			<item>
			<title>1x09 - Protección perruna de testigo</title>
			<torrent>magnet:?xt=urn:btih:3FD124E18E1C31900130437AC2BD5E0E69D743FE&dn=HDTV</torrent>
			</item>
======================================================================
			"Tag=  TORRENTTEMP1, "
			<item>
			<title>1x10 - Caninos perdidos</title>
			<torrent>magnet:?xt=urn:btih:40951F1412E4D73A28AD8B41251BAAEE912561F6&dn=HD720</torrent>	magnet:?xt=urn:btih:DC8C5BD8810C5D895E344AA4BA90B48DFC2C68D9&dn=HDTV
			</item>
======================================================================
			"Tag=  TORRENTTEMP1, "
			<item>
			<title>1x11 - Hooch contra los robots</title>
			<torrent>magnet:?xt=urn:btih:42421164597996E8A7F6DEC7577B0EDC4B978B15&dn=HD720</torrent>	magnet:?xt=urn:btih:0887A8518154C0C51BB4F59E29A04871CAA4674A&dn=HDTV
			</item>
======================================================================
			"Tag=  TORRENTTEMP1, "
			<item>
			<title>1x12 - Bite Club</title>
			<torrent>magnet:?xt=urn:btih:BB88E71E94EC6C222E82F77D792CDCA8F2C2D859&dn=HD720</torrent>	
			</item>
======================================================================
======================================================================
======================================================================
======================================================================