 <?xml version="1.0" encoding="UTF-8" standalone="yes"?>

======================================================================

<!--
 THE LIBERATOR
-->
<!--

	ETIQUETAS:
	
	- 1SerieTitle:"THE LIBERATOR", SerieTemp:"MINI SERIE", SerieID:"SERIETEMP1", SerieIDT:"TORRENTTEMP1", SerieThumbail:"https://www.themoviedb.org/t/p/original/hc7YdVV0xhpO7I6ObKHO8hO3RpG.jpg",

	
-->
======================================================================
			"Tag= TORRENTTEMP1, "
			<item>
			<title> - [COLOR yellow]CALIDAD 720</title>      
			<torrent></torrent>
			</item>
======================================================================
			"Tag= TORRENTTEMP1, "
			<item>
			<title> - Capitulos 1 a 4</title>      
			<torrent>magnet:?xt=urn:btih:4AD7AA26F71AE87BD8FFD029723D73F029CA0B45</torrent>
			</item>
======================================================================
			"Tag= TORRENTTEMP1, "
			<item>
			<title> - </title>      
			<torrent></torrent>
			</item>
======================================================================
			"Tag= TORRENTTEMP1, "
			<item>
			<title> - [COLOR yellow]CALIDAD HDTV</title>      
			<torrent></torrent>
			</item>
======================================================================
			"Tag= TORRENTTEMP1, "
			<item>
			<title> - Capitulos 1 a 4</title>      
			<torrent>magnet:?xt=urn:btih:18A5B5E4621FEA5B2CC45EB1D291D799E76CDE1B</torrent>
			</item>
======================================================================
======================================================================
======================================================================